tiktok_api_client/__init__.py
tiktok_api_client/main.py
tiktok_api_client/test_tiktok.py
tiktok_api_client/utils.py
tiktok_api_client-0.0.15.dist-info/LICENSE
tiktok_api_client-0.0.15.dist-info/METADATA
tiktok_api_client-0.0.15.dist-info/WHEEL
tiktok_api_client-0.0.15.dist-info/top_level.txt
tiktok_api_client-0.0.15.dist-info/RECORD
