Metadata-Version: 2.1
Name: tiktok_api_client
Version: 0.0.15
Summary: A Python project for TikTok content publishing
Home-page: https://github.com/mymi14s/tiktok_api_client
Author: Emmanuel Anthony
Author-email: Emmanuel Anthony <mymi14s@hotmail.com>
License: MIT
Project-URL: Homepage, https://github.com/mymi14s/tiktok_api_client
Keywords: tiktok,api,video
Classifier: License :: OSI Approved :: MIT License
Classifier: Programming Language :: Python
Classifier: Programming Language :: Python :: 3
Classifier: Programming Language :: Python :: 3.8
Requires-Python: >=3.8
License-File: LICENSE
Provides-Extra: dev
Requires-Dist: black; extra == "dev"
Requires-Dist: bumpver; extra == "dev"
Requires-Dist: isort; extra == "dev"
Requires-Dist: pip-tools; extra == "dev"
Requires-Dist: pytest; extra == "dev"
